setup.py
jmf_distribution/Binomialdistribution.py
jmf_distribution/Gaussiandistribution.py
jmf_distribution/Generaldistribution.py
jmf_distribution/__init__.py
jmf_distribution.egg-info/PKG-INFO
jmf_distribution.egg-info/SOURCES.txt
jmf_distribution.egg-info/dependency_links.txt
jmf_distribution.egg-info/not-zip-safe
jmf_distribution.egg-info/top_level.txt