Metadata-Version: 1.0
Name: jmf-distribution
Version: 0.1
Summary: Gaussian and Binomial distributions
Home-page: UNKNOWN
Author: James Michael Fritz
Author-email: jamesmichael0444@gmail.com
License: UNKNOWN
Platform: UNKNOWN
